nonebot_plugin_wenan/__init__.py
nonebot_plugin_wenan/config.py
nonebot_plugin_wenan-1.2.dist-info/LICENSE
nonebot_plugin_wenan-1.2.dist-info/METADATA
nonebot_plugin_wenan-1.2.dist-info/WHEEL
nonebot_plugin_wenan-1.2.dist-info/RECORD
