Metadata-Version: 2.3
Name: nonebot-plugin-wenan
Version: 1.2
Summary: 
Author: Q1351998764
Author-email: 57926506+Q1351998764@users.noreply.github.com
Requires-Python: >=3.10,<4.0
Classifier: Programming Language :: Python :: 3
Classifier: Programming Language :: Python :: 3.10
Classifier: Programming Language :: Python :: 3.11
Classifier: Programming Language :: Python :: 3.12
Classifier: Programming Language :: Python :: 3.13
Requires-Dist: httpx (>=0.23.3)
Requires-Dist: nonebot-adapter-onebot (>=2.2.3)
Requires-Dist: nonebot2 (>=2.0.0)
Requires-Dist: pydantic (>=1.10.7)
Requires-Dist: pyyaml (>=6.0)
